README.txt
setup.py
django_traversal.egg-info/PKG-INFO
django_traversal.egg-info/SOURCES.txt
django_traversal.egg-info/dependency_links.txt
django_traversal.egg-info/requires.txt
django_traversal.egg-info/top_level.txt
traversal/__init__.py
traversal/api.py
traversal/decorators.py
traversal/resource.py
traversal/router.py
traversal/traverse.py
traversal/urls.py
traversal/templatetags/__init__.py
traversal/templatetags/traversal_url.py